crosslink/__init__.py
crosslink/identifiers.py
crosslink/service.py
crosslink/services.py
crosslink/utils.py
crosslink/services/__init__.py
crosslink/services/github.py
crosslink/services/gitlab.py
crosslink/services/gravatar.py
crosslink/services/gravatar_hash.py
crosslink/services/keybase.py
crosslink/services/libravatar.py
crosslink/services/openhub.py
crosslink/services/origin.py
crosslink-0.2.0.dist-info/DESCRIPTION.rst
crosslink-0.2.0.dist-info/METADATA
crosslink-0.2.0.dist-info/RECORD
crosslink-0.2.0.dist-info/WHEEL
crosslink-0.2.0.dist-info/metadata.json
crosslink-0.2.0.dist-info/top_level.txt
