Metadata-Version: 2.0
Name: crosslink
Version: 0.2.0
Summary: crosslink identities.
Home-page: https://github.com/jayvdb/crosslink
Author: John Vandenberg
Author-email: jayvdb@gmail.com
License: MIT
Keywords: github gitlab bitbucket keybase openhub
Platform: UNKNOWN
Classifier: Development Status :: 3 - Alpha
Classifier: Environment :: Console
Classifier: Intended Audience :: Developers
Classifier: License :: OSI Approved :: MIT License
Classifier: Operating System :: OS Independent
Classifier: Programming Language :: Python
Classifier: Programming Language :: Python :: 2
Classifier: Programming Language :: Python :: 3
Classifier: Topic :: Software Development :: Libraries :: Python Modules
Classifier: Topic :: Software Development :: Quality Assurance
